dataclass_deser/__init__.py
dataclass_deser/deser.py
dataclass_deser-0.1.0a2.dist-info/LICENSE.txt
dataclass_deser-0.1.0a2.dist-info/METADATA
dataclass_deser-0.1.0a2.dist-info/WHEEL
dataclass_deser-0.1.0a2.dist-info/top_level.txt
dataclass_deser-0.1.0a2.dist-info/RECORD
