Metadata-Version: 2.1
Name: dataclass-deser
Version: 0.1.0a2
Summary: A simple deserialization library, based on dataclasses and type-hints
Author: Techcable
License: MIT License
Project-URL: Bug Tracker, https://github.com/Techcable/dataclass-deser/issues
Project-URL: Source Code, https://github.com/Techcable/dataclass-deser
Keywords: dataclasses,config,serialize,json,toml
Classifier: Development Status :: 2 - Pre-Alpha
Classifier: Intended Audience :: Developers
Classifier: License :: OSI Approved :: MIT License
Classifier: Programming Language :: Python :: 3
Requires-Python: >=3.10
License-File: LICENSE.txt
Requires-Dist: typing-extensions >=4.5
Provides-Extra: dev
Requires-Dist: test ; extra == 'dev'
Requires-Dist: mypy ; extra == 'dev'
Requires-Dist: black ; extra == 'dev'
Requires-Dist: isort ; extra == 'dev'
Provides-Extra: mypy
Requires-Dist: mypy >=1 ; extra == 'mypy'
Provides-Extra: test
Requires-Dist: pytest ; extra == 'test'
